shardgather/db.py
shardgather/cli.py
shardgather/__init__.py
shardgather/renderers.py
shardgather/config.ini.sample
shardgather-1.0.3.data/scripts/shardgather
shardgather-1.0.3.dist-info/DESCRIPTION.rst
shardgather-1.0.3.dist-info/top_level.txt
shardgather-1.0.3.dist-info/WHEEL
shardgather-1.0.3.dist-info/METADATA
shardgather-1.0.3.dist-info/pydist.json
shardgather-1.0.3.dist-info/RECORD
shardgather-1.0.3.dist-info/entry_points.txt
