Metadata-Version: 2.0
Name: shardgather
Version: 1.0.3
Summary: A tool for executing SQL queries against sharded databases
Home-page: https://github.com/kevinjqiu/shardgather
Author: Kevin Jing Qiu
Author-email: kevin@idempotent.ca
License: BSD
Keywords: shardgather
Platform: UNKNOWN
Classifier: Development Status :: 4 - Beta
Classifier: Intended Audience :: Developers
Classifier: License :: OSI Approved :: BSD License
Classifier: Natural Language :: English
Classifier: Programming Language :: Python :: 2
Classifier: Programming Language :: Python :: 2.6
Classifier: Programming Language :: Python :: 2.7
Classifier: Programming Language :: Python :: 3
Classifier: Programming Language :: Python :: 3.3
Requires-Dist: wheel (==0.22.0)
Requires-Dist: prettytable (==0.7.2)
Requires-Dist: pygments (==1.6)
Requires-Dist: pymysql (==0.6.2)
